juham_systemstatus/__init__.py
juham_systemstatus/py.typed
juham_systemstatus/systemstatus.py
juham_systemstatus/systemstatus_plugin.py
juham_systemstatus-0.1.14.dist-info/licenses/LICENSE.rst
juham_systemstatus-0.1.14.dist-info/METADATA
juham_systemstatus-0.1.14.dist-info/WHEEL
juham_systemstatus-0.1.14.dist-info/entry_points.txt
juham_systemstatus-0.1.14.dist-info/top_level.txt
juham_systemstatus-0.1.14.dist-info/RECORD
