Metadata-Version: 2.4
Name: juham-systemstatus
Version: 0.1.14
Summary: Built-in system diagnosis for JuhaM
Author-email: J Meskanen <juham.api@gmail.com>
Maintainer-email: "J. Meskanen" <juham.api@gmail.com>
License-Expression: MIT
Project-URL: Homepage, https://gitlab.com/juham/juham/juham-systemstatus
Project-URL: Bug Reports, https://gitlab.com/juham/juham/juham-systemstatus
Project-URL: Funding, https://meskanen.com
Project-URL: Say Thanks!, http://meskanen.com
Project-URL: Source, https://gitlab.com/juham/juham/juham-systemstatus
Keywords: object-oriented,plugin,framework
Classifier: Development Status :: 3 - Alpha
Classifier: Intended Audience :: Developers
Classifier: Topic :: Software Development
Classifier: Programming Language :: Python :: 3.8
Requires-Python: >=3.8
License-File: LICENSE.rst
Requires-Dist: juham-core>=0.2.6
Requires-Dist: pytz>=2024.1
Requires-Dist: psutil>=5.9.0
Requires-Dist: importlib-metadata
Provides-Extra: dev
Requires-Dist: check-manifest; extra == "dev"
Dynamic: license-file
